finn/__init__.py
finn/__init__.pyi
finn/__main__.py
finn/_check_numpy_version.py
finn/_event_loop.py
finn/_pydantic_compat.py
finn/_version.py
finn/conftest.py
finn/types.py
finn/view_layers.py
finn/viewer.py
finn/window.py
finn/_app_model/__init__.py
finn/_app_model/_app.py
finn/_app_model/utils.py
finn/_app_model/_tests/test_app.py
finn/_app_model/_tests/test_constants.py
finn/_app_model/_tests/test_context.py
finn/_app_model/actions/__init__.py
finn/_app_model/actions/_layerlist_context_actions.py
finn/_app_model/constants/__init__.py
finn/_app_model/constants/_menus.py
finn/_app_model/context/__init__.py
finn/_app_model/context/_context.py
finn/_app_model/context/_context_keys.py
finn/_app_model/context/_layerlist_context.py
finn/_qt/__init__.py
finn/_qt/qt_event_filters.py
finn/_qt/qt_event_loop.py
finn/_qt/qt_main_window.py
finn/_qt/qt_viewer.py
finn/_qt/qthreading.py
finn/_qt/utils.py
finn/_qt/_qapp_model/__init__.py
finn/_qt/_qapp_model/_menus.py
finn/_qt/_qapp_model/_tests/test_debug_menu.py
finn/_qt/_qapp_model/_tests/test_dummy_actions.py
finn/_qt/_qapp_model/_tests/test_file_menu.py
finn/_qt/_qapp_model/_tests/test_help_menu.py
finn/_qt/_qapp_model/_tests/test_layerlist_context_actions.py
finn/_qt/_qapp_model/_tests/test_processors.py
finn/_qt/_qapp_model/_tests/test_qaction_layer.py
finn/_qt/_qapp_model/_tests/test_qapp_model_menus.py
finn/_qt/_qapp_model/_tests/test_qproviders.py
finn/_qt/_qapp_model/_tests/test_togglers.py
finn/_qt/_qapp_model/_tests/test_view_menu.py
finn/_qt/_qapp_model/_tests/test_window_menu.py
finn/_qt/_qapp_model/_tests/utils.py
finn/_qt/_qapp_model/injection/__init__.py
finn/_qt/_qapp_model/injection/_qprocessors.py
finn/_qt/_qapp_model/injection/_qproviders.py
finn/_qt/_qapp_model/qactions/__init__.py
finn/_qt/_qapp_model/qactions/_debug.py
finn/_qt/_qapp_model/qactions/_file.py
finn/_qt/_qapp_model/qactions/_help.py
finn/_qt/_qapp_model/qactions/_layerlist_context.py
finn/_qt/_qapp_model/qactions/_layers_actions.py
finn_viewer-0.3.0.dist-info/licenses/LICENSE
finn_viewer-0.3.0.dist-info/METADATA
finn_viewer-0.3.0.dist-info/WHEEL
finn_viewer-0.3.0.dist-info/entry_points.txt
finn_viewer-0.3.0.dist-info/top_level.txt
finn_viewer-0.3.0.dist-info/RECORD
